NCryptoTools/__init__.py
NCryptoTools/jim/__init__.py
NCryptoTools/jim/jim_constants.py
NCryptoTools/jim/jim_core.py
NCryptoTools/jim/jim_encryption.py
NCryptoTools/logger/__init__.py
NCryptoTools/logger/log.py
NCryptoTools/logger/log_config.py
NCryptoTools/qt/__init__.py
NCryptoTools/qt/stylesheet_manager.py
NCryptoTools/tests/__init__.py
NCryptoTools/tests/test_file.py
NCryptoTools/tests/test_jim_core.py
NCryptoTools/tests/test_meta_singleton.py
NCryptoTools/tests/test_utilities.py
NCryptoTools/tools/__init__.py
NCryptoTools/tools/file.py
NCryptoTools/tools/file_manager.py
NCryptoTools/tools/instances_holder.py
NCryptoTools/tools/meta_singleton.py
NCryptoTools/tools/utilities.py
NCryptoTools-0.5.10.dist-info/METADATA
NCryptoTools-0.5.10.dist-info/RECORD
NCryptoTools-0.5.10.dist-info/WHEEL
NCryptoTools-0.5.10.dist-info/top_level.txt
