Metadata-Version: 2.1
Name: NCryptoTools
Version: 0.5.10
Summary: A set of tools needed for both NCryptoClient and NCryptoServer applications
Home-page: UNKNOWN
Author: Andrew Krylov
Author-email: AndrewKrylovNegovsky@gmail.com
License: GNU General Public License v3.0
Keywords: JSON,Logger,Tools,FileManager,Utilities,Qt
Platform: UNKNOWN
